{
    "players": [
      {
        "name": "Kalamburger",
        "points":0,
        "megapoint":0,
        "games": [
          { "name": "Шахматы", "firstPlace": 0, "secondPlace": 0, "thirdPlace": 0, "fourthPlace": 0 },
          { "name": "Шашки", "firstPlace": 0, "secondPlace": 0, "thirdPlace": 0, "fourthPlace": 0 },
          { "name": "Blur", "firstPlace": 0, "secondPlace": 0, "thirdPlace": 0, "fourthPlace": 0 },
          { "name": "Дурак", "firstPlace": 0, "secondPlace": 0, "thirdPlace": 0, "fourthPlace": 0 },
          { "name": "Монополия", "firstPlace": 0, "secondPlace": 0, "thirdPlace": 0, "fourthPlace": 0 },
          { "name": "Ping Pong", "firstPlace": 0, "secondPlace": 0, "thirdPlace": 0, "fourthPlace": 0 },
          { "name": "Покер", "firstPlace": 0, "secondPlace": 0, "thirdPlace": 0, "fourthPlace": 0 },
          { "name": "Викторина", "firstPlace": 0, "secondPlace": 0, "thirdPlace": 0, "fourthPlace": 0 },
          { "name": "Bottle Flip", "firstPlace": 0, "secondPlace": 0, "thirdPlace": 0, "fourthPlace": 0 },
          { "name": "Бойцовская арена", "firstPlace": 0, "secondPlace": 0, "thirdPlace": 0, "fourthPlace": 0 },
          { "name": "Бильярд", "firstPlace": 0, "secondPlace": 0, "thirdPlace": 0, "fourthPlace": 0 },
          { "name": "Крестики-нолики", "firstPlace": 0, "secondPlace": 0, "thirdPlace": 0, "fourthPlace": 0 },
          { "name": "Uno", "firstPlace": 0, "secondPlace": 0, "thirdPlace": 0, "fourthPlace": 0 },
          { "name": "Тетрис", "firstPlace": 0, "secondPlace": 0, "thirdPlace": 0, "fourthPlace": 0 },
          { "name": "Секретная игра", "firstPlace": 0, "secondPlace": 0, "thirdPlace": 0, "fourthPlace": 0 },
          { "name": "Дартс", "firstPlace": 0, "secondPlace": 0, "thirdPlace": 0, "fourthPlace": 0 },
          { "name": "Rusted Warfare", "firstPlace": 0, "secondPlace": 0, "thirdPlace": 0, "fourthPlace": 0 },
          { "name": "Blackjack", "firstPlace": 0, "secondPlace": 0, "thirdPlace": 0, "fourthPlace": 0 },
          { "name": "Завоевание Фортуны", "firstPlace": 0, "secondPlace": 0, "thirdPlace": 0, "fourthPlace": 0 },
          { "name": "Blocksudoku", "firstPlace": 0, "secondPlace": 0, "thirdPlace": 0, "fourthPlace": 0 }
        ]
      },
      {
        "name": "Betito",
        "points":0,
        "megapoint":0,
        "games": [
          { "name": "Шахматы", "firstPlace": 0, "secondPlace": 0, "thirdPlace": 0, "fourthPlace": 0 },
          { "name": "Шашки", "firstPlace": 0, "secondPlace": 0, "thirdPlace": 0, "fourthPlace": 0 },
          { "name": "Blur", "firstPlace": 0, "secondPlace": 0, "thirdPlace": 0, "fourthPlace": 0 },
          { "name": "Дурак", "firstPlace": 0, "secondPlace": 0, "thirdPlace": 0, "fourthPlace": 0 },
          { "name": "Монополия", "firstPlace": 0, "secondPlace": 0, "thirdPlace": 0, "fourthPlace": 0 },
          { "name": "Ping Pong", "firstPlace": 0, "secondPlace": 0, "thirdPlace": 0, "fourthPlace": 0 },
          { "name": "Покер", "firstPlace": 0, "secondPlace": 0, "thirdPlace": 0, "fourthPlace": 0 },
          { "name": "Викторина", "firstPlace": 0, "secondPlace": 0, "thirdPlace": 0, "fourthPlace": 0 },
          { "name": "Bottle Flip", "firstPlace": 0, "secondPlace": 0, "thirdPlace": 0, "fourthPlace": 0 },
          { "name": "Бойцовская арена", "firstPlace": 0, "secondPlace": 0, "thirdPlace": 0, "fourthPlace": 0 },
          { "name": "Бильярд", "firstPlace": 0, "secondPlace": 0, "thirdPlace": 0, "fourthPlace": 0 },
          { "name": "Крестики-нолики", "firstPlace": 0, "secondPlace": 0, "thirdPlace": 0, "fourthPlace": 0 },
          { "name": "Uno", "firstPlace": 0, "secondPlace": 0, "thirdPlace": 0, "fourthPlace": 0 },
          { "name": "Тетрис", "firstPlace": 0, "secondPlace": 0, "thirdPlace": 0, "fourthPlace": 0 },
          { "name": "Секретная игра", "firstPlace": 0, "secondPlace": 0, "thirdPlace": 0, "fourthPlace": 0 },
          { "name": "Дартс", "firstPlace": 0, "secondPlace": 0, "thirdPlace": 0, "fourthPlace": 0 },
          { "name": "Rusted Warfare", "firstPlace": 0, "secondPlace": 0, "thirdPlace": 0, "fourthPlace": 0 },
          { "name": "Blackjack", "firstPlace": 0, "secondPlace": 0, "thirdPlace": 0, "fourthPlace": 0 },
          { "name": "Завоевание Фортуны", "firstPlace": 0, "secondPlace": 0, "thirdPlace": 0, "fourthPlace": 0 },
          { "name": "Blocksudoku", "firstPlace": 0, "secondPlace": 0, "thirdPlace": 0, "fourthPlace": 0 }
        ]
      },
      {
        "name": "Gorbatic",
        "points":0,
        "megapoint":0,
        "games": [
          { "name": "Шахматы", "firstPlace": 0, "secondPlace": 0, "thirdPlace": 0, "fourthPlace": 0 },
          { "name": "Шашки", "firstPlace": 0, "secondPlace": 0, "thirdPlace": 0, "fourthPlace": 0 },
          { "name": "Blur", "firstPlace": 0, "secondPlace": 0, "thirdPlace": 0, "fourthPlace": 0 },
          { "name": "Дурак", "firstPlace": 0, "secondPlace": 0, "thirdPlace": 0, "fourthPlace": 0 },
          { "name": "Монополия", "firstPlace": 0, "secondPlace": 0, "thirdPlace": 0, "fourthPlace": 0 },
          { "name": "Ping Pong", "firstPlace": 0, "secondPlace": 0, "thirdPlace": 0, "fourthPlace": 0 },
          { "name": "Покер", "firstPlace": 0, "secondPlace": 0, "thirdPlace": 0, "fourthPlace": 0 },
          { "name": "Викторина", "firstPlace": 0, "secondPlace": 0, "thirdPlace": 0, "fourthPlace": 0 },
          { "name": "Bottle Flip", "firstPlace": 0, "secondPlace": 0, "thirdPlace": 0, "fourthPlace": 0 },
          { "name": "Бойцовская арена", "firstPlace": 0, "secondPlace": 0, "thirdPlace": 0, "fourthPlace": 0 },
          { "name": "Бильярд", "firstPlace": 0, "secondPlace": 0, "thirdPlace": 0, "fourthPlace": 0 },
          { "name": "Крестики-нолики", "firstPlace": 0, "secondPlace": 0, "thirdPlace": 0, "fourthPlace": 0 },
          { "name": "Uno", "firstPlace": 0, "secondPlace": 0, "thirdPlace": 0, "fourthPlace": 0 },
          { "name": "Тетрис", "firstPlace": 0, "secondPlace": 0, "thirdPlace": 0, "fourthPlace": 0 },
          { "name": "Секретная игра", "firstPlace": 0, "secondPlace": 0, "thirdPlace": 0, "fourthPlace": 0 },
          { "name": "Дартс", "firstPlace": 0, "secondPlace": 0, "thirdPlace": 0, "fourthPlace": 0 },
          { "name": "Rusted Warfare", "firstPlace": 0, "secondPlace": 0, "thirdPlace": 0, "fourthPlace": 0 },
          { "name": "Blackjack", "firstPlace": 0, "secondPlace": 0, "thirdPlace": 0, "fourthPlace": 0 },
          { "name": "Завоевание Фортуны", "firstPlace": 0, "secondPlace": 0, "thirdPlace": 0, "fourthPlace": 0 },
          { "name": "Blocksudoku", "firstPlace": 0, "secondPlace": 0, "thirdPlace": 0, "fourthPlace": 0 }
        ]
      },
      {
        "name": "CFKN",
        "points":0 ,
        "megapoint":0,
        "games": [
          { "name": "Шахматы", "firstPlace": 0, "secondPlace": 0, "thirdPlace": 0, "fourthPlace": 0 },
          { "name": "Шашки", "firstPlace": 0, "secondPlace": 0, "thirdPlace": 0, "fourthPlace": 0 },
          { "name": "Blur", "firstPlace": 0, "secondPlace": 0, "thirdPlace": 0, "fourthPlace": 0 },
          { "name": "Дурак", "firstPlace": 0, "secondPlace": 0, "thirdPlace": 0, "fourthPlace": 0 },
          { "name": "Монополия", "firstPlace": 0, "secondPlace": 0, "thirdPlace": 0, "fourthPlace": 0 },
          { "name": "Ping Pong", "firstPlace": 0, "secondPlace": 0, "thirdPlace": 0, "fourthPlace": 0 },
          { "name": "Покер", "firstPlace": 0, "secondPlace": 0, "thirdPlace": 0, "fourthPlace": 0 },
          { "name": "Викторина", "firstPlace": 0, "secondPlace": 0, "thirdPlace": 0, "fourthPlace": 0 },
          { "name": "Bottle Flip", "firstPlace": 0, "secondPlace": 0, "thirdPlace": 0, "fourthPlace": 0 },
          { "name": "Бойцовская арена", "firstPlace": 0, "secondPlace": 0, "thirdPlace": 0, "fourthPlace": 0 },
          { "name": "Бильярд", "firstPlace": 0, "secondPlace": 0, "thirdPlace": 0, "fourthPlace": 0 },
          { "name": "Крестики-нолики", "firstPlace": 0, "secondPlace": 0, "thirdPlace": 0, "fourthPlace": 0 },
          { "name": "Uno", "firstPlace": 0, "secondPlace": 0, "thirdPlace": 0, "fourthPlace": 0 },
          { "name": "Тетрис", "firstPlace": 0, "secondPlace": 0, "thirdPlace": 0, "fourthPlace": 0 },
          { "name": "Секретная игра", "firstPlace": 0, "secondPlace": 0, "thirdPlace": 0, "fourthPlace": 0 },
          { "name": "Дартс", "firstPlace": 0, "secondPlace": 0, "thirdPlace": 0, "fourthPlace": 0 },
          { "name": "Rusted Warfare", "firstPlace": 0, "secondPlace": 0, "thirdPlace": 0, "fourthPlace": 0 },
          { "name": "Blackjack", "firstPlace": 0, "secondPlace": 0, "thirdPlace": 0, "fourthPlace": 0 },
          { "name": "Завоевание Фортуны", "firstPlace": 0, "secondPlace": 0, "thirdPlace": 0, "fourthPlace": 0 },
          { "name": "Blocksudoku", "firstPlace": 0, "secondPlace": 0, "thirdPlace": 0, "fourthPlace": 0 }
        ]
      }
    ]
  }
  